{ "TABLE":[{ "ROW":[ { "COL":[ {"DATA":"GA HKXB CHO LON"},{"DATA":"Trang Tử"},{"DATA":"5"},{"DATA":"680705.376632056"},{"DATA":"1188961.82298208"},{"DATA":"4301"},{"DATA":"0"},{"DATA":"BX14"}]}, { "COL":[ {"DATA":"27"},{"DATA":"Tháp Mười"},{"DATA":"6"},{"DATA":"680705.784254045"},{"DATA":"1188843.13449715"},{"DATA":"8819"},{"DATA":"1"},{"DATA":"Q6T032"}]}, { "COL":[ {"DATA":"13C-13D"},{"DATA":"Tháp Mười"},{"DATA":"6"},{"DATA":"680759.267577251"},{"DATA":"1188854.06157734"},{"DATA":"8820"},{"DATA":"2"},{"DATA":"Q6T033"}]}, { "COL":[ {"DATA":"327"},{"DATA":"Hải Thượng Lãn Ông"},{"DATA":"5"},{"DATA":"680881.395402544"},{"DATA":"1188880.80757794"},{"DATA":"8693"},{"DATA":"3"},{"DATA":"Q5T017"}]}, { "COL":[ {"DATA":"11-12"},{"DATA":"Hải Thượng Lãn Ông"},{"DATA":"5"},{"DATA":"680976.550667914"},{"DATA":"1188903.61866778"},{"DATA":"8694"},{"DATA":"4"},{"DATA":"Q5T018"}]}, { "COL":[ {"DATA":"14-16"},{"DATA":"Châu Văn Liêm"},{"DATA":"5"},{"DATA":"681431.475265778"},{"DATA":"1188978.36226709"},{"DATA":"8687"},{"DATA":"5"},{"DATA":"Q5T011"}]}, { "COL":[ {"DATA":"68"},{"DATA":"Châu Văn Liêm"},{"DATA":"5"},{"DATA":"681401.237026019"},{"DATA":"1189110.89709676"},{"DATA":"8688"},{"DATA":"6"},{"DATA":"Q5T012"}]}, { "COL":[ {"DATA":"359"},{"DATA":"Hồng Bàng"},{"DATA":"5"},{"DATA":"681433.405842964"},{"DATA":"1189326.84108313"},{"DATA":"8707"},{"DATA":"7"},{"DATA":"Q5T031"}]}, { "COL":[ {"DATA":"217"},{"DATA":"Hồng Bàng"},{"DATA":"5"},{"DATA":"681866.251712856"},{"DATA":"1189413.93211637"},{"DATA":"8708"},{"DATA":"8"},{"DATA":"Q5T032"}]}, { "COL":[ {"DATA":"215"},{"DATA":"Hồng Bàng"},{"DATA":"5"},{"DATA":"682031.390255238"},{"DATA":"1189447.61924127"},{"DATA":"8709"},{"DATA":"9"},{"DATA":"Q5T033"}]}, { "COL":[ {"DATA":"121"},{"DATA":"An Dương Vương"},{"DATA":"5"},{"DATA":"682663.766450545"},{"DATA":"1189581.93065414"},{"DATA":"8682"},{"DATA":"10"},{"DATA":"Q5T006"}]}, { "COL":[ {"DATA":"59C"},{"DATA":"An Dương Vương"},{"DATA":"5"},{"DATA":"682925.238086429"},{"DATA":"1189636.04042001"},{"DATA":"8683"},{"DATA":"11"},{"DATA":"Q5T007"}]}, { "COL":[ {"DATA":"407A"},{"DATA":"An Dương Vương"},{"DATA":"5"},{"DATA":"683346.672723274"},{"DATA":"1189770.81861544"},{"DATA":"8684"},{"DATA":"12"},{"DATA":"Q5T008"}]}, { "COL":[ {"DATA":"373"},{"DATA":"An Dương Vương"},{"DATA":"5"},{"DATA":"683520.18782289"},{"DATA":"1189840.84852787"},{"DATA":"8685"},{"DATA":"13"},{"DATA":"Q5T009"}]}, { "COL":[ {"DATA":"273-275"},{"DATA":"An Dương Vương"},{"DATA":"5"},{"DATA":"683969.270636925"},{"DATA":"1190029.34540135"},{"DATA":"8686"},{"DATA":"14"},{"DATA":"Q5T010"}]}, { "COL":[ {"DATA":"211-213"},{"DATA":"Nguyễn Văn Cừ"},{"DATA":"5"},{"DATA":"684077.222418206"},{"DATA":"1190022.21369224"},{"DATA":"8754"},{"DATA":"15"},{"DATA":"Q5T085"}]}, { "COL":[ {"DATA":"373A"},{"DATA":"Nguyễn Trãi"},{"DATA":"1"},{"DATA":"684259.742723383"},{"DATA":"1189934.12413651"},{"DATA":"6554"},{"DATA":"16"},{"DATA":"Q1T149"}]}, { "COL":[ {"DATA":"333"},{"DATA":"Nguyễn Trãi"},{"DATA":"1"},{"DATA":"684399.259697041"},{"DATA":"1190171.35437724"},{"DATA":"6555"},{"DATA":"17"},{"DATA":"Q1T150"}]}, { "COL":[ {"DATA":"173 - 173B"},{"DATA":"Nguyễn Cư Trinh"},{"DATA":"1"},{"DATA":"684597.970939684"},{"DATA":"1190285.75977527"},{"DATA":"6560"},{"DATA":"18"},{"DATA":"Q1T155"}]}, { "COL":[ {"DATA":"37"},{"DATA":"Nguyễn Cư Trinh"},{"DATA":"1"},{"DATA":"684986.61768901"},{"DATA":"1190446.97568961"},{"DATA":"6561"},{"DATA":"19"},{"DATA":"Q1T156"}]}, { "COL":[ {"DATA":"227 - 229"},{"DATA":"Trần Hưng Đạo"},{"DATA":"1"},{"DATA":"685127.557298895"},{"DATA":"1190530.0956358"},{"DATA":"6541"},{"DATA":"20"},{"DATA":"Q1T136"}]}, { "COL":[ {"DATA":"135"},{"DATA":"Trần Hưng Đạo"},{"DATA":"1"},{"DATA":"685328.302940356"},{"DATA":"1190768.02924718"},{"DATA":"6542"},{"DATA":"21"},{"DATA":"Q1T137"}]}, { "COL":[ {"DATA":"71C"},{"DATA":"Trần Hưng Đạo"},{"DATA":"1"},{"DATA":"685423.24748547"},{"DATA":"1190880.33497906"},{"DATA":"6543"},{"DATA":"22"},{"DATA":"Q1T138"}]}, { "COL":[ {"DATA":"57"},{"DATA":"Phạm Ngũ Lão"},{"DATA":"1"},{"DATA":"685700.788468858"},{"DATA":"1191111.33420284"},{"DATA":"6450"},{"DATA":"23"},{"DATA":"Q1T043"}]}, { "COL":[ {"DATA":"163"},{"DATA":"Hàm Nghi"},{"DATA":"1"},{"DATA":"685834.166256209"},{"DATA":"1191156.74188996"},{"DATA":"6423"},{"DATA":"24"},{"DATA":"Q1T015"}]}, { "COL":[ {"DATA":"89A"},{"DATA":"Hàm Nghi"},{"DATA":"1"},{"DATA":"686092.757988671"},{"DATA":"1191145.86192695"},{"DATA":"6424"},{"DATA":"25"},{"DATA":"Q1T016"}]}, { "COL":[ {"DATA":"67"},{"DATA":"Hàm Nghi"},{"DATA":"1"},{"DATA":"686336.912327375"},{"DATA":"1191133.08247194"},{"DATA":"10569"},{"DATA":"26"},{"DATA":"Q1T169"}]}, { "COL":[ {"DATA":"Bến thủy nội địa Thủ Thiêm"},{"DATA":"Tôn Đức Thắng"},{"DATA":"1"},{"DATA":"686603.241652831"},{"DATA":"1191497.73870805"},{"DATA":"6430"},{"DATA":"27"},{"DATA":"Q1T023"}]}, { "COL":[ {"DATA":"Đối diện số 5"},{"DATA":"Tôn Đức Thắng"},{"DATA":"1"},{"DATA":"686647.35313628"},{"DATA":"1191860.35413907"},{"DATA":"6431"},{"DATA":"28"},{"DATA":"Q1T024"}]}, { "COL":[ {"DATA":"Đối diện số 3C"},{"DATA":"Tôn Đức Thắng"},{"DATA":"1"},{"DATA":"686727.807175385"},{"DATA":"1192163.05372194"},{"DATA":"6432"},{"DATA":"29"},{"DATA":"Q1T025"}]}, { "COL":[ {"DATA":"2"},{"DATA":"Tôn Đức Thắng"},{"DATA":"1"},{"DATA":"686624.513618631"},{"DATA":"1192379.03584232"},{"DATA":"6433"},{"DATA":"30"},{"DATA":"Q1T026"}]}, { "COL":[ {"DATA":"Hông nhà máy Bason"},{"DATA":"Nguyễn Hữu Cảnh"},{"DATA":"1"},{"DATA":"686636.533381277"},{"DATA":"1192512.01011585"},{"DATA":"6438"},{"DATA":"31"},{"DATA":"Q1T031"}]}, { "COL":[ {"DATA":"2A"},{"DATA":"Nguyễn Hữu Cảnh"},{"DATA":"1"},{"DATA":"686813.540630841"},{"DATA":"1192729.5534464"},{"DATA":"6439"},{"DATA":"32"},{"DATA":"Q1T032"}]}, { "COL":[ {"DATA":"18"},{"DATA":"Nguyễn Hữu Cảnh"},{"DATA":"Bình Thạnh"},{"DATA":"687057.344802828"},{"DATA":"1193200.45601678"},{"DATA":"6954"},{"DATA":"33"},{"DATA":"QBTHT080"}]}, { "COL":[ {"DATA":"176E"},{"DATA":"Nguyễn Hữu Cảnh"},{"DATA":"Bình Thạnh"},{"DATA":"687891.911623493"},{"DATA":"1193648.43774748"},{"DATA":"6955"},{"DATA":"34"},{"DATA":"QBTHT081"}]}, { "COL":[ {"DATA":"794"},{"DATA":"Quốc lộ 52"},{"DATA":"2"},{"DATA":"689602.295447252"},{"DATA":"1194411.35396672"},{"DATA":"9986"},{"DATA":"35"},{"DATA":"Q2T076"}]}, { "COL":[ {"DATA":"Đối diện ngã 3 Thảo Điền"},{"DATA":"Quốc lộ 52"},{"DATA":"2"},{"DATA":"690116.55985518"},{"DATA":"1194509.43417948"},{"DATA":"9987"},{"DATA":"36"},{"DATA":"Q2T077"}]}, { "COL":[ {"DATA":"170"},{"DATA":"Quốc lộ 52"},{"DATA":"2"},{"DATA":"690556.453736328"},{"DATA":"1194595.65862854"},{"DATA":"9988"},{"DATA":"37"},{"DATA":"Q2T078"}]}, { "COL":[ {"DATA":"Chung cư Estella"},{"DATA":"Quốc lộ 52"},{"DATA":"2"},{"DATA":"691118.809792027"},{"DATA":"1194708.96592781"},{"DATA":"9989"},{"DATA":"38"},{"DATA":"Q2T079"}]}, { "COL":[ {"DATA":"249B"},{"DATA":"Quốc lộ 52"},{"DATA":"9"},{"DATA":"692228.120904513"},{"DATA":"1196539.11271525"},{"DATA":"10188"},{"DATA":"39"},{"DATA":"Q9T196"}]}, { "COL":[ {"DATA":"185A"},{"DATA":"Quốc lộ 52"},{"DATA":"9"},{"DATA":"692488.710973855"},{"DATA":"1197294.69860295"},{"DATA":"10189"},{"DATA":"40"},{"DATA":"Q9T197"}]}, { "COL":[ {"DATA":"354A"},{"DATA":"Quốc lộ 52"},{"DATA":"9"},{"DATA":"692731.512383275"},{"DATA":"1197738.27090933"},{"DATA":"10190"},{"DATA":"41"},{"DATA":"Q9T198"}]}, { "COL":[ {"DATA":"Trước Khu QLGTĐT số 2"},{"DATA":"Quốc lộ 52"},{"DATA":"9"},{"DATA":"692927.481201753"},{"DATA":"1198100.33503974"},{"DATA":"10191"},{"DATA":"42"},{"DATA":"Q9T199"}]}, { "COL":[ {"DATA":"Đối diện 461"},{"DATA":"Nguyên Văn Bá"},{"DATA":"Thủ Đức"},{"DATA":"693051.787839947"},{"DATA":"1198423.00379318"},{"DATA":"10537"},{"DATA":"43"},{"DATA":"QTDT060"}]}, { "COL":[ {"DATA":"Đối diện 23-25 "},{"DATA":"Đặng Văn Bi"},{"DATA":"Thủ Đức"},{"DATA":"693123.375357617"},{"DATA":"1198748.57049634"},{"DATA":"10536"},{"DATA":"44"},{"DATA":"QTDT061"}]}, { "COL":[ {"DATA":"Kế 50"},{"DATA":"Đặng Văn Bi"},{"DATA":"Thủ Đức"},{"DATA":"692856.3236963"},{"DATA":"1199029.47826192"},{"DATA":"10294"},{"DATA":"45"},{"DATA":"QTDT062"}]}, { "COL":[ {"DATA":"Đối diện 139"},{"DATA":"Đặng Văn Bi"},{"DATA":"Thủ Đức"},{"DATA":"692667.980698682"},{"DATA":"1199276.74521301"},{"DATA":"10295"},{"DATA":"46"},{"DATA":"QTDT063"}]}, { "COL":[ {"DATA":"Trường mầm non Họa Mi"},{"DATA":"Đặng Văn Bi"},{"DATA":"Thủ Đức"},{"DATA":"692401.240288442"},{"DATA":"1199716.68959496"},{"DATA":"10296"},{"DATA":"47"},{"DATA":"QTDT064"}]}, { "COL":[ {"DATA":"238-240"},{"DATA":"Đặng Văn Bi"},{"DATA":"Thủ Đức"},{"DATA":"692260.859698864"},{"DATA":"1199951.11688344"},{"DATA":"10297"},{"DATA":"48"},{"DATA":"QTDT065"}]}, { "COL":[ {"DATA":"100"},{"DATA":"Võ Văn Ngân"},{"DATA":"Thủ Đức"},{"DATA":"692405.666367476"},{"DATA":"1200003.67941237"},{"DATA":"10309"},{"DATA":"49"},{"DATA":"QTDT077"}]}, { "COL":[ {"DATA":"190"},{"DATA":"Võ Văn Ngân"},{"DATA":"Thủ Đức"},{"DATA":"692845.457917398"},{"DATA":"1200031.2872625"},{"DATA":"10310"},{"DATA":"50"},{"DATA":"QTDT078"}]}, { "COL":[ {"DATA":"274-276"},{"DATA":"Võ Văn Ngân"},{"DATA":"Thủ Đức"},{"DATA":"693388.713345782"},{"DATA":"1199919.91815664"},{"DATA":"10311"},{"DATA":"51"},{"DATA":"QTDT079"}]}, { "COL":[ {"DATA":"4-6"},{"DATA":"Lê Văn Việt"},{"DATA":"9"},{"DATA":"694039.31368233"},{"DATA":"1199759.93445831"},{"DATA":"10065"},{"DATA":"52"},{"DATA":"Q9T073"}]}, { "COL":[ {"DATA":"50"},{"DATA":"Lê Văn Việt"},{"DATA":"9"},{"DATA":"694430.208360703"},{"DATA":"1199522.96711424"},{"DATA":"10066"},{"DATA":"53"},{"DATA":"Q9T074"}]}, { "COL":[ {"DATA":"188"},{"DATA":"Lê Văn Việt"},{"DATA":"9"},{"DATA":"694806.870318555"},{"DATA":"1199313.31126922"},{"DATA":"10067"},{"DATA":"54"},{"DATA":"Q9T075"}]}, { "COL":[ {"DATA":"278"},{"DATA":"Lê Văn Việt"},{"DATA":"9"},{"DATA":"695054.097077348"},{"DATA":"1199319.1306921"},{"DATA":"10068"},{"DATA":"55"},{"DATA":"Q9T076"}]}, { "COL":[ {"DATA":"424A-424B"},{"DATA":"Lê Văn Việt"},{"DATA":"9"},{"DATA":"695555.80159545"},{"DATA":"1199344.80542962"},{"DATA":"10069"},{"DATA":"56"},{"DATA":"Q9T077"}]}, { "COL":[ {"DATA":"Đối diện A1/6"},{"DATA":"Lê Văn Việt"},{"DATA":"9"},{"DATA":"695785.007235643"},{"DATA":"1199372.67200197"},{"DATA":"10070"},{"DATA":"57"},{"DATA":"Q9T078"}]}, { "COL":[ {"DATA":"Đối diện 451"},{"DATA":"Lê Văn Việt"},{"DATA":"9"},{"DATA":"696098.703822835"},{"DATA":"1199447.37312722"},{"DATA":"10071"},{"DATA":"58"},{"DATA":"Q9T079"}]} ]}]}