{ "TABLE":[{ "ROW":[ { "COL":[ {"DATA":"Bến xe Ngã Tư Ga"},{"DATA":"Quốc lộ 1A"},{"DATA":"12"},{"DATA":"683459.995075839"},{"DATA":"1201244.56714907"},{"DATA":"10615"},{"DATA":"1"},{"DATA":"BX37"}]}, { "COL":[ {"DATA":"96/2"},{"DATA":"Quốc lộ 1A"},{"DATA":"Quận 12"},{"DATA":"683108.188828507"},{"DATA":"1201212.75916307"},{"DATA":"8327"},{"DATA":"2"},{"DATA":"Q12T062"}]}, { "COL":[ {"DATA":"972"},{"DATA":"Quốc lộ 1A"},{"DATA":"Quận 12"},{"DATA":"682820.79598329"},{"DATA":"1201209.50112553"},{"DATA":"8328"},{"DATA":"3"},{"DATA":"Q12T063"}]}, { "COL":[ {"DATA":"Khách sạn Thạnh Xuân"},{"DATA":"Quốc lộ 1A"},{"DATA":"Quận 12"},{"DATA":"682093.387659791"},{"DATA":"1201198.22208444"},{"DATA":"8329"},{"DATA":"4"},{"DATA":"Q12T064"}]}, { "COL":[ {"DATA":"Khách sạn Phi Vũ"},{"DATA":"Quốc lộ 1A"},{"DATA":"Quận 12"},{"DATA":"681481.082488766"},{"DATA":"1201188.60747785"},{"DATA":"8330"},{"DATA":"5"},{"DATA":"Q12T065"}]}, { "COL":[ {"DATA":"1360"},{"DATA":"Quốc lộ 1A"},{"DATA":"Quận 12"},{"DATA":"681210.256003806"},{"DATA":"1201199.80449385"},{"DATA":"8331"},{"DATA":"6"},{"DATA":"Q12T066"}]}, { "COL":[ {"DATA":"Quận ủy Quận 12"},{"DATA":"Quốc lộ 1A"},{"DATA":"Quận 12"},{"DATA":"680846.506733552"},{"DATA":"1201216.32522479"},{"DATA":"8332"},{"DATA":"7"},{"DATA":"Q12T067"}]}, { "COL":[ {"DATA":"1572-1678"},{"DATA":"Quốc lộ 1A"},{"DATA":"Quận 12"},{"DATA":"680441.748694059"},{"DATA":"1201237.43473782"},{"DATA":"8333"},{"DATA":"8"},{"DATA":"Q12T068"}]}, { "COL":[ {"DATA":"Kế chùa Phước Thiện An"},{"DATA":"Lê Đức Thọ"},{"DATA":"Quận 12"},{"DATA":"680361.790444612"},{"DATA":"1201055.98167173"},{"DATA":"8345"},{"DATA":"9"},{"DATA":"Q12T080"}]}, { "COL":[ {"DATA":"139/1552A"},{"DATA":"Lê Đức Thọ"},{"DATA":"Gò Vấp"},{"DATA":"680810.277458417"},{"DATA":"1200611.72931948"},{"DATA":"9528"},{"DATA":"11"},{"DATA":"QGVT062"}]}, { "COL":[ {"DATA":"Đối diện 2/10G"},{"DATA":"Lê Văn Thọ"},{"DATA":"Gò Vấp"},{"DATA":"681010.019186366"},{"DATA":"1200338.91388216"},{"DATA":"9616"},{"DATA":"12"},{"DATA":"QGVT150"}]}, { "COL":[ {"DATA":"13/7"},{"DATA":"Lê Văn Thọ"},{"DATA":"Gò Vấp"},{"DATA":"681064.926466499"},{"DATA":"1199842.39411087"},{"DATA":"9617"},{"DATA":"13"},{"DATA":"QGVT151"}]}, { "COL":[ {"DATA":"104D"},{"DATA":"Lê Văn Thọ"},{"DATA":"Gò Vấp"},{"DATA":"681121.852080634"},{"DATA":"1199460.10453827"},{"DATA":"9618"},{"DATA":"14"},{"DATA":"QGVT152"}]}, { "COL":[ {"DATA":"197"},{"DATA":"Lê Văn Thọ"},{"DATA":"Gò Vấp"},{"DATA":"681142.352378435"},{"DATA":"1199142.30313757"},{"DATA":"9619"},{"DATA":"15"},{"DATA":"QGVT153"}]}, { "COL":[ {"DATA":"57"},{"DATA":"Lê Văn Thọ"},{"DATA":"Gò Vấp"},{"DATA":"681215.57475211"},{"DATA":"1198621.97005303"},{"DATA":"9620"},{"DATA":"16"},{"DATA":"QGVT154"}]}, { "COL":[ {"DATA":"9"},{"DATA":"Quang Trung"},{"DATA":"Gò Vấp"},{"DATA":"681607.438840996"},{"DATA":"1198295.69233693"},{"DATA":"9650"},{"DATA":"17"},{"DATA":"QGVT184"}]}, { "COL":[ {"DATA":"1/5-1/8"},{"DATA":"Quang Trung"},{"DATA":"Gò Vấp"},{"DATA":"681812.201774894"},{"DATA":"1198234.74003599"},{"DATA":"9651"},{"DATA":"18"},{"DATA":"QGVT185"}]}, { "COL":[ {"DATA":"37/8A"},{"DATA":"Quang Trung"},{"DATA":"Gò Vấp"},{"DATA":"682136.512434822"},{"DATA":"1198034.85765915"},{"DATA":"9652"},{"DATA":"19"},{"DATA":"QGVT186"}]}, { "COL":[ {"DATA":"5T"},{"DATA":"Quang Trung"},{"DATA":"Gò Vấp"},{"DATA":"682473.504778549"},{"DATA":"1197769.47846066"},{"DATA":"9653"},{"DATA":"20"},{"DATA":"QGVT187"}]}, { "COL":[ {"DATA":"201-201C"},{"DATA":"Quang Trung"},{"DATA":"Gò Vấp"},{"DATA":"682790.388132188"},{"DATA":"1197588.49952542"},{"DATA":"9654"},{"DATA":"21"},{"DATA":"QGVT188"}]}, { "COL":[ {"DATA":"127"},{"DATA":"Quang Trung"},{"DATA":"Gò Vấp"},{"DATA":"683096.933243994"},{"DATA":"1197474.78215076"},{"DATA":"9655"},{"DATA":"22"},{"DATA":"QGVT189"}]}, { "COL":[ {"DATA":"9-11"},{"DATA":"Quang Trung"},{"DATA":"Gò Vấp"},{"DATA":"683352.584121036"},{"DATA":"1197389.05424432"},{"DATA":"9656"},{"DATA":"23"},{"DATA":"QGVT190"}]}, { "COL":[ {"DATA":"Đối diện A2"},{"DATA":"Quang Trung"},{"DATA":"Gò Vấp"},{"DATA":"683568.292860227"},{"DATA":"1197313.01620621"},{"DATA":"9657"},{"DATA":"24"},{"DATA":"QGVT191"}]}, { "COL":[ {"DATA":"Đối diện 792A"},{"DATA":"Nguyễn Kiệm"},{"DATA":"Gò Vấp"},{"DATA":"683630.383999798"},{"DATA":"1197223.01882403"},{"DATA":"9589"},{"DATA":"25"},{"DATA":"QGVT123"}]}, { "COL":[ {"DATA":"629B"},{"DATA":"Nguyễn Kiệm"},{"DATA":"Gò Vấp"},{"DATA":"683531.359795577"},{"DATA":"1196775.72730826"},{"DATA":"9590"},{"DATA":"26"},{"DATA":"QGVT124"}]}, { "COL":[ {"DATA":"167-169"},{"DATA":"Nguyễn Kiệm"},{"DATA":"Gò Vấp"},{"DATA":"683525.508699638"},{"DATA":"1196453.09028529"},{"DATA":"9591"},{"DATA":"27"},{"DATA":"QGVT125"}]}, { "COL":[ {"DATA":"37-39"},{"DATA":"Nguyễn Kiệm"},{"DATA":"Gò Vấp"},{"DATA":"683516.626027678"},{"DATA":"1196041.54821907"},{"DATA":"9592"},{"DATA":"28"},{"DATA":"QGVT126"}]}, { "COL":[ {"DATA":"117"},{"DATA":"Nguyễn Thái Sơn"},{"DATA":"Gò Vấp"},{"DATA":"683352.533723292"},{"DATA":"1196010.92040437"},{"DATA":"8261"},{"DATA":"29"},{"DATA":"QGVT052"}]}, { "COL":[ {"DATA":"61"},{"DATA":"Bạch Đằng"},{"DATA":"Tân Bình"},{"DATA":"682778.929254428"},{"DATA":"1195986.50022525"},{"DATA":"7433"},{"DATA":"30"},{"DATA":"QTBT174"}]}, { "COL":[ {"DATA":"43"},{"DATA":"Hồng Hà"},{"DATA":"Tân Bình"},{"DATA":"682578.601234552"},{"DATA":"1195877.28418736"},{"DATA":"7428"},{"DATA":"31"},{"DATA":"QTBT169"}]}, { "COL":[ {"DATA":"Đối diện 8"},{"DATA":"Hồng Hà"},{"DATA":"Tân Bình"},{"DATA":"682212.695325651"},{"DATA":"1195847.89047209"},{"DATA":"7429"},{"DATA":"32"},{"DATA":"QTBT170"}]}, { "COL":[ {"DATA":"63"},{"DATA":"Trường Sơn"},{"DATA":"Tân Bình"},{"DATA":"681994.917900292"},{"DATA":"1195495.53076587"},{"DATA":"7272"},{"DATA":"33"},{"DATA":"QTBT012"}]}, { "COL":[ {"DATA":"Siêu thị super Bow"},{"DATA":"Trường Sơn"},{"DATA":"Tân Bình"},{"DATA":"681975.716630037"},{"DATA":"1195251.20674691"},{"DATA":"7273"},{"DATA":"34"},{"DATA":"QTBT013"}]}, { "COL":[ {"DATA":"20"},{"DATA":"Trần Quốc Hoàn"},{"DATA":"Tân Bình"},{"DATA":"681740.092989328"},{"DATA":"1194511.42689332"},{"DATA":"7370"},{"DATA":"35"},{"DATA":"QTBT110"}]}, { "COL":[ {"DATA":"71"},{"DATA":"Trần Quốc Hoàn"},{"DATA":"Tân Bình"},{"DATA":"681916.77347077"},{"DATA":"1194763.60748645"},{"DATA":"7372"},{"DATA":"36"},{"DATA":"QTBT112"}]}, { "COL":[ {"DATA":"216"},{"DATA":"Hoàng Văn Thụ"},{"DATA":"Tân Bình"},{"DATA":"681514.654665446"},{"DATA":"1194324.55493132"},{"DATA":"7298"},{"DATA":"37"},{"DATA":"QTBT038"}]}, { "COL":[ {"DATA":"340H"},{"DATA":"Hoàng Văn Thụ"},{"DATA":"Tân Bình"},{"DATA":"681158.078871846"},{"DATA":"1193977.84631153"},{"DATA":"7299"},{"DATA":"38"},{"DATA":"QTBT039"}]}, { "COL":[ {"DATA":"B9"},{"DATA":"Xuân Diệu"},{"DATA":"Tân Bình"},{"DATA":"680966.906394116"},{"DATA":"1193921.80072023"},{"DATA":"7324"},{"DATA":"39"},{"DATA":"QTBT064"}]}, { "COL":[ {"DATA":"E62"},{"DATA":"Xuân Hồng"},{"DATA":"Tân Bình"},{"DATA":"680821.905280528"},{"DATA":"1193898.21082376"},{"DATA":"7325"},{"DATA":"40"},{"DATA":"QTBT065"}]}, { "COL":[ {"DATA":"23"},{"DATA":"Xuân Hồng"},{"DATA":"Tân Bình"},{"DATA":"680655.23476134"},{"DATA":"1193731.91605799"},{"DATA":"7326"},{"DATA":"41"},{"DATA":"QTBT066"}]}, { "COL":[ {"DATA":"Đối diện 544"},{"DATA":"Cách Mạng Tháng 8"},{"DATA":"Tân Bình"},{"DATA":"680896.487834673"},{"DATA":"1193491.24823993"},{"DATA":"7319"},{"DATA":"42"},{"DATA":"QTBT059"}]}, { "COL":[ {"DATA":"1057"},{"DATA":"Cách Mạng Tháng 8"},{"DATA":"Tân Bình"},{"DATA":"681128.745601393"},{"DATA":"1193368.49467293"},{"DATA":"7320"},{"DATA":"43"},{"DATA":"QTBT060"}]}, { "COL":[ {"DATA":"1003"},{"DATA":"Cách Mạng Tháng 8"},{"DATA":"Tân Bình"},{"DATA":"681487.414404507"},{"DATA":"1193182.23630412"},{"DATA":"7321"},{"DATA":"44"},{"DATA":"QTBT061"}]}, { "COL":[ {"DATA":"907"},{"DATA":"Cách Mạng Tháng 8"},{"DATA":"Tân Bình"},{"DATA":"681572.812659729"},{"DATA":"1193135.26585456"},{"DATA":"7322"},{"DATA":"45"},{"DATA":"QTBT062"}]}, { "COL":[ {"DATA":"771"},{"DATA":"Cách Mạng Tháng 8"},{"DATA":"Tân Bình"},{"DATA":"681749.917905947"},{"DATA":"1193041.14177902"},{"DATA":"7323"},{"DATA":"46"},{"DATA":"QTBT063"}]}, { "COL":[ {"DATA":"Công Viên Lê Thị Riêng"},{"DATA":"Cách Mạng Tháng 8"},{"DATA":"10"},{"DATA":"682117.929060455"},{"DATA":"1192845.05508065"},{"DATA":"10543"},{"DATA":"47"},{"DATA":"Q10T090"}]}, { "COL":[ {"DATA":"Đối diện 69"},{"DATA":"Trường Sơn"},{"DATA":"Quận 10"},{"DATA":"682128.41753718"},{"DATA":"1192655.00278704"},{"DATA":"8672"},{"DATA":"48"},{"DATA":"Q10T106"}]}, { "COL":[ {"DATA":"BB14ter"},{"DATA":"Trường Sơn"},{"DATA":"Quận 10"},{"DATA":"681904.692919561"},{"DATA":"1192366.41117864"},{"DATA":"8667"},{"DATA":"49"},{"DATA":"Q10T101"}]}, { "COL":[ {"DATA":"F4"},{"DATA":"Trường Sơn"},{"DATA":"Quận 10"},{"DATA":"681699.662007341"},{"DATA":"1192281.21213555"},{"DATA":"8668"},{"DATA":"50"},{"DATA":"Q10T102"}]}, { "COL":[ {"DATA":"XX1"},{"DATA":"Đồng Nai"},{"DATA":"Quận 10"},{"DATA":"681764.364760997"},{"DATA":"1192061.65836254"},{"DATA":"8664"},{"DATA":"51"},{"DATA":"Q10T098"}]}, { "COL":[ {"DATA":"197B27"},{"DATA":"Thành Thái nối dài"},{"DATA":"Quận 10"},{"DATA":"681730.960559856"},{"DATA":"1191892.43023472"},{"DATA":"8666"},{"DATA":"52"},{"DATA":"Q10T100"}]}, { "COL":[ {"DATA":"136"},{"DATA":"Tô Hiến Thành"},{"DATA":"Quận 10"},{"DATA":"681813.020485917"},{"DATA":"1191653.27516165"},{"DATA":"8639"},{"DATA":"53"},{"DATA":"Q10T072"}]}, { "COL":[ {"DATA":"350 ( cũ 142)"},{"DATA":"Tô Hiến Thành"},{"DATA":"Quận 10"},{"DATA":"681628.947517164"},{"DATA":"1191408.02986581"},{"DATA":"8638"},{"DATA":"54"},{"DATA":"Q10T071"}]}, { "COL":[ {"DATA":"142 kios 37-38"},{"DATA":"Tô Hiến Thành"},{"DATA":"Quận 10"},{"DATA":"681407.74299241"},{"DATA":"1191176.88397299"},{"DATA":"8637"},{"DATA":"55"},{"DATA":"Q10T070"}]}, { "COL":[ {"DATA":"Đối diện 266"},{"DATA":"Lý Thường Kiệt"},{"DATA":"Quận 11"},{"DATA":"681321.469689904"},{"DATA":"1190998.89495628"},{"DATA":"8487"},{"DATA":"56"},{"DATA":"Q11T019"}]}, { "COL":[ {"DATA":"215C"},{"DATA":"Lý Thường Kiệt"},{"DATA":"Quận 11"},{"DATA":"681440.528147575"},{"DATA":"1190573.99354363"},{"DATA":"8488"},{"DATA":"57"},{"DATA":"Q11T020"}]}, { "COL":[ {"DATA":"940 (6B)"},{"DATA":"3 tháng 2"},{"DATA":"Quận 11"},{"DATA":"681423.727563122"},{"DATA":"1190317.40675257"},{"DATA":"8469"},{"DATA":"58"},{"DATA":"Q11T001"}]}, { "COL":[ {"DATA":"970"},{"DATA":"3 tháng 2"},{"DATA":"Quận 11"},{"DATA":"681105.212833875"},{"DATA":"1190138.76038368"},{"DATA":"8470"},{"DATA":"59"},{"DATA":"Q11T002"}]}, { "COL":[ {"DATA":"1114A-1116A"},{"DATA":"3 tháng 2"},{"DATA":"Quận 11"},{"DATA":"680814.475017076"},{"DATA":"1189976.88047681"},{"DATA":"8471"},{"DATA":"60"},{"DATA":"Q11T003"}]}, { "COL":[ {"DATA":"193"},{"DATA":"Tạ Uyên"},{"DATA":"Quận 11"},{"DATA":"680800.33096249"},{"DATA":"1189716.22353723"},{"DATA":"8554"},{"DATA":"61"},{"DATA":"Q11T086"}]}, { "COL":[ {"DATA":"79"},{"DATA":"Tạ Uyên"},{"DATA":"5"},{"DATA":"680825.277903888"},{"DATA":"1189399.78217572"},{"DATA":"8758"},{"DATA":"62"},{"DATA":"Q5T089"}]}, { "COL":[ {"DATA":"266"},{"DATA":"Hồng Bàng"},{"DATA":"5"},{"DATA":"680705.62161323"},{"DATA":"1189215.21291183"},{"DATA":"8704"},{"DATA":"63"},{"DATA":"Q5T028"}]}, { "COL":[ {"DATA":"GA HKXB CHO LON"},{"DATA":"Trang Tử"},{"DATA":"5"},{"DATA":"680705.376632056"},{"DATA":"1188961.82298208"},{"DATA":"4301"},{"DATA":"64"},{"DATA":"BX14"}]}, { "COL":[ {"DATA":"GA HKXB CHO LON"},{"DATA":"Trang Tử"},{"DATA":"5"},{"DATA":"680705.376632056"},{"DATA":"1188961.82298208"},{"DATA":"4301"},{"DATA":"65"},{"DATA":"BX14"}]} ]}]}