{ "TABLE":[{ "ROW":[ { "COL":[ {"DATA":"Bến xe buýt Khu A Đô thị Quốc gia"},{"DATA":"Khu A Đô thị Quốc gia"},{"DATA":"Thủ Đức"},{"DATA":"697310.512208495"},{"DATA":"1202752.39506597"},{"DATA":"6315"},{"DATA":"0"},{"DATA":"BX87"}]}, { "COL":[ {"DATA":"Nhà máy Tiến Thành"},{"DATA":"Quốc lộ 1A "},{"DATA":"Thủ Đức"},{"DATA":"697495.834656298"},{"DATA":"1202283.73648406"},{"DATA":"10416"},{"DATA":"1"},{"DATA":"QTDT186"}]}, { "COL":[ {"DATA":"Trường giáo dục Quốc phòng"},{"DATA":"Quốc lộ 1A "},{"DATA":"Thủ Đức"},{"DATA":"697233.59786465"},{"DATA":"1201993.76883314"},{"DATA":"10417"},{"DATA":"2"},{"DATA":"QTDT187"}]}, { "COL":[ {"DATA":"9/29"},{"DATA":"Quốc lộ 1A "},{"DATA":"Thủ Đức"},{"DATA":"696883.166939071"},{"DATA":"1201750.19402072"},{"DATA":"10418"},{"DATA":"3"},{"DATA":"QTDT188"}]}, { "COL":[ {"DATA":"35B"},{"DATA":"Quốc lộ 1A "},{"DATA":"Thủ Đức"},{"DATA":"696094.623247102"},{"DATA":"1201668.2357075"},{"DATA":"10419"},{"DATA":"4"},{"DATA":"QTDT189"}]}, { "COL":[ {"DATA":"Đối diện 1026-1028"},{"DATA":"Quốc lộ 1A "},{"DATA":"Thủ Đức"},{"DATA":"695782.341465008"},{"DATA":"1201842.32403093"},{"DATA":"10420"},{"DATA":"5"},{"DATA":"QTDT190"}]}, { "COL":[ {"DATA":"Kế 21"},{"DATA":"Quốc lộ 1A "},{"DATA":"Thủ Đức"},{"DATA":"695302.897642986"},{"DATA":"1201890.34933692"},{"DATA":"10421"},{"DATA":"6"},{"DATA":"QTDT191"}]}, { "COL":[ {"DATA":"Kế 59/6"},{"DATA":"Quốc lộ 1A "},{"DATA":"Thủ Đức"},{"DATA":"694807.192707258"},{"DATA":"1201936.02768121"},{"DATA":"10422"},{"DATA":"7"},{"DATA":"QTDT192"}]}, { "COL":[ {"DATA":"Đại học Kinh tế -Luật"},{"DATA":"Quốc lộ 1A "},{"DATA":"Thủ Đức"},{"DATA":"694337.935385827"},{"DATA":"1202086.04031639"},{"DATA":"10423"},{"DATA":"8"},{"DATA":"QTDT193"}]}, { "COL":[ {"DATA":"Trung tâm kho vận Linh Xuân"},{"DATA":"Quốc lộ 1A "},{"DATA":"Thủ Đức"},{"DATA":"694009.643845856"},{"DATA":"1202191.93482752"},{"DATA":"10424"},{"DATA":"9"},{"DATA":"QTDT194"}]}, { "COL":[ {"DATA":"Cột điện NG/1"},{"DATA":"Quốc lộ 1A "},{"DATA":"Thủ Đức"},{"DATA":"693787.133279978"},{"DATA":"1202264.13820231"},{"DATA":"10425"},{"DATA":"10"},{"DATA":"QTDT195"}]}, { "COL":[ {"DATA":"Đối diện công ty Nissan"},{"DATA":"Quốc lộ 1A "},{"DATA":"Thủ Đức"},{"DATA":"693561.600874252"},{"DATA":"1202339.23887136"},{"DATA":"10426"},{"DATA":"11"},{"DATA":"QTDT196"}]}, { "COL":[ {"DATA":"559"},{"DATA":"Quốc lộ 1A "},{"DATA":"Thủ Đức"},{"DATA":"692603.680757954"},{"DATA":"1202653.46238125"},{"DATA":"10427"},{"DATA":"12"},{"DATA":"QTDT197"}]}, { "COL":[ {"DATA":"467B"},{"DATA":"Quốc lộ 1A "},{"DATA":"Thủ Đức"},{"DATA":"692233.686160936"},{"DATA":"1202759.05546954"},{"DATA":"10428"},{"DATA":"13"},{"DATA":"QTDT198"}]}, { "COL":[ {"DATA":"Đối diện 20B/8"},{"DATA":"Quốc lộ 1A"},{"DATA":"Thủ Đức"},{"DATA":"692079.381267871"},{"DATA":"1202787.51894958"},{"DATA":"10540"},{"DATA":"14"},{"DATA":"QTDT199"}]}, { "COL":[ {"DATA":"275"},{"DATA":"Quốc lộ 1A "},{"DATA":"Thủ Đức"},{"DATA":"690906.125087861"},{"DATA":"1202602.20454872"},{"DATA":"10429"},{"DATA":"15"},{"DATA":"QTDT201"}]}, { "COL":[ {"DATA":"251B"},{"DATA":"Quốc lộ 1A "},{"DATA":"Thủ Đức"},{"DATA":"690663.460995625"},{"DATA":"1202521.91793118"},{"DATA":"10430"},{"DATA":"16"},{"DATA":"QTDT202"}]}, { "COL":[ {"DATA":"179"},{"DATA":"Quốc lộ 1A "},{"DATA":"Thủ Đức"},{"DATA":"690185.620195317"},{"DATA":"1202384.92207523"},{"DATA":"10431"},{"DATA":"17"},{"DATA":"QTDT203"}]}, { "COL":[ {"DATA":"Đối diện Bưu điện Tam Bình"},{"DATA":"Quốc lộ 1A "},{"DATA":"Thủ Đức"},{"DATA":"689591.208032497"},{"DATA":"1202233.49926109"},{"DATA":"10432"},{"DATA":"18"},{"DATA":"QTDT204"}]}, { "COL":[ {"DATA":"Chợ đầu mối nông sản Thủ Đức"},{"DATA":"Quốc lộ 1A "},{"DATA":"Thủ Đức"},{"DATA":"688999.428195402"},{"DATA":"1201928.10605682"},{"DATA":"10433"},{"DATA":"19"},{"DATA":"QTDT205"}]}, { "COL":[ {"DATA":"777"},{"DATA":"Quốc lộ 13"},{"DATA":"Thủ Đức"},{"DATA":"688504.490433223"},{"DATA":"1201455.50573853"},{"DATA":"10451"},{"DATA":"20"},{"DATA":"QTDT223"}]}, { "COL":[ {"DATA":"Đối diện 782"},{"DATA":"Quốc lộ 13"},{"DATA":"Thủ Đức"},{"DATA":"688494.011951203"},{"DATA":"1201182.99743007"},{"DATA":"10452"},{"DATA":"21"},{"DATA":"QTDT224"}]}, { "COL":[ {"DATA":"715"},{"DATA":"Quốc lộ 13"},{"DATA":"Thủ Đức"},{"DATA":"688432.225948732"},{"DATA":"1201010.72622063"},{"DATA":"10453"},{"DATA":"22"},{"DATA":"QTDT225"}]}, { "COL":[ {"DATA":"645"},{"DATA":"Quốc lộ 13"},{"DATA":"Thủ Đức"},{"DATA":"688272.697572161"},{"DATA":"1200593.12942684"},{"DATA":"10454"},{"DATA":"23"},{"DATA":"QTDT226"}]}, { "COL":[ {"DATA":"607"},{"DATA":"Quốc lộ 13"},{"DATA":"Thủ Đức"},{"DATA":"688101.240293478"},{"DATA":"1200209.55490384"},{"DATA":"10455"},{"DATA":"24"},{"DATA":"QTDT227"}]}, { "COL":[ {"DATA":"557A"},{"DATA":"Quốc lộ 13"},{"DATA":"Thủ Đức"},{"DATA":"687839.683255864"},{"DATA":"1199783.50700283"},{"DATA":"10456"},{"DATA":"25"},{"DATA":"QTDT228"}]}, { "COL":[ {"DATA":"447-449"},{"DATA":"Quốc lộ 13"},{"DATA":"Thủ Đức"},{"DATA":"687814.477366687"},{"DATA":"1199312.74788095"},{"DATA":"10457"},{"DATA":"26"},{"DATA":"QTDT229"}]}, { "COL":[ {"DATA":"385"},{"DATA":"Quốc lộ 13"},{"DATA":"Thủ Đức"},{"DATA":"687681.966664605"},{"DATA":"1198937.83366877"},{"DATA":"10458"},{"DATA":"27"},{"DATA":"QTDT230"}]}, { "COL":[ {"DATA":"327-329"},{"DATA":"Quốc lộ 13"},{"DATA":"Thủ Đức"},{"DATA":"687475.773431452"},{"DATA":"1198677.60881566"},{"DATA":"10459"},{"DATA":"28"},{"DATA":"QTDT231"}]}, { "COL":[ {"DATA":"261"},{"DATA":"Quốc lộ 13"},{"DATA":"Thủ Đức"},{"DATA":"687345.318298224"},{"DATA":"1198353.11603899"},{"DATA":"10460"},{"DATA":"29"},{"DATA":"QTDT232"}]}, { "COL":[ {"DATA":"173"},{"DATA":"Quốc lộ 13"},{"DATA":"Thủ Đức"},{"DATA":"687362.949491391"},{"DATA":"1198034.40761792"},{"DATA":"10461"},{"DATA":"30"},{"DATA":"QTDT233"}]}, { "COL":[ {"DATA":"328/5 (Đại học Luật)"},{"DATA":"Quốc lộ 13"},{"DATA":"Thủ Đức"},{"DATA":"687379.418787702"},{"DATA":"1197713.64968117"},{"DATA":"10462"},{"DATA":"31"},{"DATA":"QTDT234"}]}, { "COL":[ {"DATA":"78/3"},{"DATA":"Đinh Bộ Lĩnh"},{"DATA":"Bình Thạnh"},{"DATA":"687084.070854748"},{"DATA":"1196233.37325966"},{"DATA":"6914"},{"DATA":"32"},{"DATA":"QBTHT040"}]}, { "COL":[ {"DATA":"222/4 Ter"},{"DATA":"Nguyễn Xí"},{"DATA":"Bình Thạnh"},{"DATA":"687015.232599726"},{"DATA":"1195719.40958091"},{"DATA":"6948"},{"DATA":"33"},{"DATA":"QBTHT074"}]}, { "COL":[ {"DATA":"đối diện 134/4A"},{"DATA":"Ung Văn Khiêm"},{"DATA":"Bình Thạnh"},{"DATA":"687447.581877815"},{"DATA":"1195291.96334953"},{"DATA":"7007"},{"DATA":"34"},{"DATA":"QBTHT134"}]}, { "COL":[ {"DATA":"8A"},{"DATA":"Đường D2"},{"DATA":"Bình Thạnh"},{"DATA":"687610.260271395"},{"DATA":"1195104.89798121"},{"DATA":"6910"},{"DATA":"35"},{"DATA":"QBTHT036"}]}, { "COL":[ {"DATA":"74 Cư xá Văn Thánh Bắc"},{"DATA":"Đường D2"},{"DATA":"Bình Thạnh"},{"DATA":"687591.005589675"},{"DATA":"1194877.17321684"},{"DATA":"6911"},{"DATA":"36"},{"DATA":"QBTHT037"}]}, { "COL":[ {"DATA":"459"},{"DATA":"Điện Biên Phủ"},{"DATA":"Bình Thạnh"},{"DATA":"687373.388225484"},{"DATA":"1194556.23681613"},{"DATA":"6930"},{"DATA":"37"},{"DATA":"QBTHT056"}]}, { "COL":[ {"DATA":"419"},{"DATA":"Điện Biên Phủ"},{"DATA":"Bình Thạnh"},{"DATA":"687264.495138109"},{"DATA":"1194567.57580125"},{"DATA":"6929"},{"DATA":"38"},{"DATA":"QBTHT055"}]}, { "COL":[ {"DATA":"221"},{"DATA":"Xô Viết Nghệ Tĩnh"},{"DATA":"Bình Thạnh"},{"DATA":"687074.11121209"},{"DATA":"1194358.99989087"},{"DATA":"7006"},{"DATA":"39"},{"DATA":"QBTHT133"}]}, { "COL":[ {"DATA":"153"},{"DATA":"Xô Viết Nghệ Tĩnh"},{"DATA":"Bình Thạnh"},{"DATA":"687002.649667957"},{"DATA":"1194024.0167619"},{"DATA":"7005"},{"DATA":"40"},{"DATA":"QBTHT132"}]}, { "COL":[ {"DATA":"151"},{"DATA":"Xô Viết Nghệ Tĩnh"},{"DATA":"Bình Thạnh"},{"DATA":"686885.878707147"},{"DATA":"1193817.59971646"},{"DATA":"7004"},{"DATA":"41"},{"DATA":"QBTHT131"}]}, { "COL":[ {"DATA":"79"},{"DATA":"Xô Viết Nghệ Tĩnh"},{"DATA":"Bình Thạnh"},{"DATA":"686742.697882374"},{"DATA":"1193664.95323761"},{"DATA":"7003"},{"DATA":"42"},{"DATA":"QBTHT130"}]}, { "COL":[ {"DATA":"2A"},{"DATA":"Nguyễn Thị Minh Khai"},{"DATA":"1"},{"DATA":"686453.564628453"},{"DATA":"1193351.99419409"},{"DATA":"6505"},{"DATA":"43"},{"DATA":"Q1T099"}]}, { "COL":[ {"DATA":"Đối diện 9"},{"DATA":"Nguyễn Thị Minh Khai"},{"DATA":"1"},{"DATA":"686092.121680824"},{"DATA":"1192962.85470149"},{"DATA":"6506"},{"DATA":"44"},{"DATA":"Q1T100"}]}, { "COL":[ {"DATA":"43"},{"DATA":"Đinh Tiên Hoàng "},{"DATA":"1"},{"DATA":"686133.929547875"},{"DATA":"1192803.7324223"},{"DATA":"6418"},{"DATA":"45"},{"DATA":"Q1T010"}]}, { "COL":[ {"DATA":"Đối diện Central Plaza"},{"DATA":"Lê Duẫn"},{"DATA":"1"},{"DATA":"686105.111968085"},{"DATA":"1192644.65366735"},{"DATA":"6491"},{"DATA":"46"},{"DATA":"Q1T085"}]}, { "COL":[ {"DATA":"115Bis"},{"DATA":"Hai Bà Trưng"},{"DATA":"1"},{"DATA":"686067.859380679"},{"DATA":"1192102.98165266"},{"DATA":"6473"},{"DATA":"47"},{"DATA":"Q1T066"}]}, { "COL":[ {"DATA":"101"},{"DATA":"Hai Bà Trưng"},{"DATA":"1"},{"DATA":"686272.322225945"},{"DATA":"1191920.13048588"},{"DATA":"6474"},{"DATA":"48"},{"DATA":"Q1T067"}]}, { "COL":[ {"DATA":"Đối diện 4"},{"DATA":"Hai Bà Trưng"},{"DATA":"1"},{"DATA":"686506.423733943"},{"DATA":"1191709.75466865"},{"DATA":"6475"},{"DATA":"49"},{"DATA":"Q1T068"}]}, { "COL":[ {"DATA":"21"},{"DATA":"Tôn Đức Thắng"},{"DATA":"1"},{"DATA":"686580.061234348"},{"DATA":"1191424.26546278"},{"DATA":"1"},{"DATA":"50"},{"DATA":"Q1T030"}]}, { "COL":[ {"DATA":"2-4"},{"DATA":"Hàm Nghi"},{"DATA":"1"},{"DATA":"686499.300670129"},{"DATA":"1191171.14826596"},{"DATA":"6427"},{"DATA":"51"},{"DATA":"Q1T019"}]}, { "COL":[ {"DATA":"84"},{"DATA":"Hàm Nghi"},{"DATA":"1"},{"DATA":"686221.235248239"},{"DATA":"1191180.96954345"},{"DATA":"10469"},{"DATA":"52"},{"DATA":"Q1N020"}]}, { "COL":[ {"DATA":"122"},{"DATA":"Hàm Nghi"},{"DATA":"1"},{"DATA":"686055.780007294"},{"DATA":"1191187.92022262"},{"DATA":"6428"},{"DATA":"53"},{"DATA":"Q1T021"}]}, { "COL":[ {"DATA":"136"},{"DATA":"Hàm Nghi"},{"DATA":"1"},{"DATA":"685827.556591284"},{"DATA":"1191198.0214978"},{"DATA":"6429"},{"DATA":"54"},{"DATA":"Q1T022"}]}, { "COL":[ {"DATA":"Trạm Điều hành Sài Gòn- Cổng A "},{"DATA":"Quách Thị Trang"},{"DATA":"1"},{"DATA":"685721.081205467"},{"DATA":"1191188.92510903"},{"DATA":"6"},{"DATA":"56"},{"DATA":"BX02"}]} ]}]}