{ "TABLE":[{ "ROW":[ { "COL":[ {"DATA":"Sân bay Tân Sơn Nhất"},{"DATA":"Sân bay Tân Sơn Nhất"},{"DATA":"Tân Binh"},{"DATA":"681889.200267056"},{"DATA":"1195876.72552459"},{"DATA":"6365"},{"DATA":"0"},{"DATA":"BX50"}]}, { "COL":[ {"DATA":"63"},{"DATA":"Trường Sơn"},{"DATA":"Tân Bình"},{"DATA":"681994.917900292"},{"DATA":"1195495.53076587"},{"DATA":"7272"},{"DATA":"1"},{"DATA":"QTBT012"}]}, { "COL":[ {"DATA":"Siêu thị super Bow"},{"DATA":"Trường Sơn"},{"DATA":"Tân Bình"},{"DATA":"681975.716630037"},{"DATA":"1195251.20674691"},{"DATA":"7273"},{"DATA":"2"},{"DATA":"QTBT013"}]}, { "COL":[ {"DATA":"71"},{"DATA":"Trần Quốc Hoàn"},{"DATA":"Tân Bình"},{"DATA":"681916.77347077"},{"DATA":"1194763.60748645"},{"DATA":"7372"},{"DATA":"3"},{"DATA":"QTBT112"}]}, { "COL":[ {"DATA":"20"},{"DATA":"Trần Quốc Hoàn"},{"DATA":"Tân Bình"},{"DATA":"681740.092989328"},{"DATA":"1194511.42689332"},{"DATA":"7370"},{"DATA":"4"},{"DATA":"QTBT110"}]}, { "COL":[ {"DATA":"259"},{"DATA":"Hoàng Văn Thụ"},{"DATA":"Tân Bình"},{"DATA":"681851.199804265"},{"DATA":"1194415.85639095"},{"DATA":"7296"},{"DATA":"5"},{"DATA":"QTBT036"}]}, { "COL":[ {"DATA":"247"},{"DATA":"Hoàng Văn Thụ"},{"DATA":"Tân Bình"},{"DATA":"682184.288434779"},{"DATA":"1194387.65239012"},{"DATA":"7297"},{"DATA":"6"},{"DATA":"QTBT037"}]}, { "COL":[ {"DATA":"307/6"},{"DATA":"Nguyễn Văn Trỗi"},{"DATA":"Phú Nhuận"},{"DATA":"682413.447447622"},{"DATA":"1194322.16237581"},{"DATA":"8031"},{"DATA":"7"},{"DATA":"QPNT043"}]}, { "COL":[ {"DATA":"279"},{"DATA":"Nguyễn Văn Trỗi"},{"DATA":"Phú Nhuận"},{"DATA":"682685.07437655"},{"DATA":"1194161.60427497"},{"DATA":"8032"},{"DATA":"8"},{"DATA":"QPNT044"}]}, { "COL":[ {"DATA":"Khách sạn OMNI"},{"DATA":"Nguyễn Văn Trỗi"},{"DATA":"Phú Nhuận"},{"DATA":"683018.780438142"},{"DATA":"1193967.8707243"},{"DATA":"8033"},{"DATA":"9"},{"DATA":"QPNT045"}]}, { "COL":[ {"DATA":"157"},{"DATA":"Nguyễn Văn Trỗi"},{"DATA":"Phú Nhuận"},{"DATA":"683220.965088501"},{"DATA":"1193847.44536075"},{"DATA":"8034"},{"DATA":"10"},{"DATA":"QPNT046"}]}, { "COL":[ {"DATA":"101"},{"DATA":"Nguyễn Văn Trỗi"},{"DATA":"Phú Nhuận"},{"DATA":"683591.98572001"},{"DATA":"1193630.67590443"},{"DATA":"8035"},{"DATA":"34"},{"DATA":"QPNT047"}]}, { "COL":[ {"DATA":"321-323"},{"DATA":"Nam Kỳ Khởi Nghĩa"},{"DATA":"3"},{"DATA":"684013.386827362"},{"DATA":"1193308.02596114"},{"DATA":"6626"},{"DATA":"35"},{"DATA":"Q3T053"}]}, { "COL":[ {"DATA":"201A"},{"DATA":"Nam Kỳ Khởi Nghĩa"},{"DATA":"3"},{"DATA":"684413.11563447"},{"DATA":"1192941.02803966"},{"DATA":"6627"},{"DATA":"36"},{"DATA":"Q3T054"}]}, { "COL":[ {"DATA":"179"},{"DATA":"Nam Kỳ Khởi Nghĩa"},{"DATA":"3"},{"DATA":"684630.867306252"},{"DATA":"1192739.73924472"},{"DATA":"6628"},{"DATA":"37"},{"DATA":"Q3T055"}]}, { "COL":[ {"DATA":"159 Ter"},{"DATA":"Nam Kỳ Khởi Nghĩa"},{"DATA":"3"},{"DATA":"684931.700183892"},{"DATA":"1192474.20527997"},{"DATA":"6629"},{"DATA":"38"},{"DATA":"Q3T056"}]}, { "COL":[ {"DATA":"170"},{"DATA":"Nguyễn Đình Chiểu"},{"DATA":"3"},{"DATA":"685022.595054124"},{"DATA":"1192256.84003241"},{"DATA":"6633"},{"DATA":"39"},{"DATA":"Q3T060"}]}, { "COL":[ {"DATA":"216"},{"DATA":"Nguyễn Đình Chiểu"},{"DATA":"3"},{"DATA":"684760.674110303"},{"DATA":"1191969.10407478"},{"DATA":"6634"},{"DATA":"40"},{"DATA":"Q3T061"}]}, { "COL":[ {"DATA":"85"},{"DATA":"Cách Mạng Tháng Tám"},{"DATA":"1"},{"DATA":"684934.255493311"},{"DATA":"1191330.28966307"},{"DATA":"6412"},{"DATA":"41"},{"DATA":"Q1T004"}]}, { "COL":[ {"DATA":"Trạm Điều hành Sài Gòn- Cổng B"},{"DATA":"Quách Thị Trang"},{"DATA":"1"},{"DATA":"685721.430313471"},{"DATA":"1191158.37639347"},{"DATA":"10587"},{"DATA":"42"},{"DATA":"BX03"}]}, { "COL":[ {"DATA":"8"},{"DATA":"Trần Hưng Đạo"},{"DATA":"1"},{"DATA":"685453.759685404"},{"DATA":"1190946.08579057"},{"DATA":"6529"},{"DATA":"43"},{"DATA":"Q1T124"}]}, { "COL":[ {"DATA":"10"},{"DATA":"Trần Hưng Đạo"},{"DATA":"1"},{"DATA":"685304.314054778"},{"DATA":"1190768.84420297"},{"DATA":"6530"},{"DATA":"44"},{"DATA":"Q1T125"}]}, { "COL":[ {"DATA":"150"},{"DATA":"Trần Hưng Đạo"},{"DATA":"1"},{"DATA":"684977.917045287"},{"DATA":"1190386.08138936"},{"DATA":"6532"},{"DATA":"45"},{"DATA":"Q1T127"}]}, { "COL":[ {"DATA":"112"},{"DATA":"Trần Hưng Đạo"},{"DATA":"1"},{"DATA":"685160.541585391"},{"DATA":"1190598.77472642"},{"DATA":"6531"},{"DATA":"46"},{"DATA":"Q1T126"}]}, { "COL":[ {"DATA":"210 - 212"},{"DATA":"Trần Hưng Đạo"},{"DATA":"1"},{"DATA":"684824.935572352"},{"DATA":"1190197.37990016"},{"DATA":"6533"},{"DATA":"47"},{"DATA":"Q1T128"}]}, { "COL":[ {"DATA":"262"},{"DATA":"Trần Hưng Đạo"},{"DATA":"1"},{"DATA":"684557.144164948"},{"DATA":"1189882.34499677"},{"DATA":"6534"},{"DATA":"48"},{"DATA":"Q1T129"}]}, { "COL":[ {"DATA":"290"},{"DATA":"Trần Hưng Đạo"},{"DATA":"1"},{"DATA":"684362.552873259"},{"DATA":"1189669.14875741"},{"DATA":"6535"},{"DATA":"49"},{"DATA":"Q1T130"}]}, { "COL":[ {"DATA":"158-160"},{"DATA":"Dương Bá Trạc"},{"DATA":"8"},{"DATA":"684685.097673466"},{"DATA":"1188513.12844005"},{"DATA":"6737"},{"DATA":"50"},{"DATA":"Q8T047"}]}, { "COL":[ {"DATA":"290A/15"},{"DATA":"Dương Bá Trạc"},{"DATA":"8"},{"DATA":"684633.011739396"},{"DATA":"1188061.02353495"},{"DATA":"6738"},{"DATA":"51"},{"DATA":"Q8T048"}]}, { "COL":[ {"DATA":"128"},{"DATA":"Đường 9A"},{"DATA":"BÌnh Chánh"},{"DATA":"684726.361131571"},{"DATA":"1187447.053809"},{"DATA":"10742"},{"DATA":"52"},{"DATA":"QBCT461"}]}, { "COL":[ {"DATA":"Khu dân cư Trung Sơn"},{"DATA":"10"},{"DATA":"Binh Chánh"},{"DATA":"684706.112962307"},{"DATA":"1187073.81649174"},{"DATA":"6364"},{"DATA":"53"},{"DATA":"BX56"}]} ]}]}