{ "TABLE":[{ "ROW":[ { "COL":[ {"DATA":"1998"},{"DATA":"Vĩnh Lộc"},{"DATA":"Bình Chánh"},{"DATA":"671913.937046283"},{"DATA":"1195310.67378282"},{"DATA":"7580"},{"DATA":"1"},{"DATA":"QBCT149"}]}, { "COL":[ {"DATA":"2170"},{"DATA":"Vĩnh Lộc"},{"DATA":"Bình Chánh"},{"DATA":"672241.39879274"},{"DATA":"1195514.02232442"},{"DATA":"7581"},{"DATA":"2"},{"DATA":"QBCT150"}]}, { "COL":[ {"DATA":"D20/4/3B"},{"DATA":"Võ Văn Vân"},{"DATA":"Bình Chánh"},{"DATA":"672579.140370254"},{"DATA":"1195543.74219502"},{"DATA":"7522"},{"DATA":"3"},{"DATA":"QBCT091"}]}, { "COL":[ {"DATA":"D10/25F"},{"DATA":"Võ Văn Vân"},{"DATA":"Bình Chánh"},{"DATA":"672508.238507355"},{"DATA":"1194960.53718703"},{"DATA":"7523"},{"DATA":"4"},{"DATA":"QBCT092"}]}, { "COL":[ {"DATA":"C6/13A"},{"DATA":"Võ Văn Vân"},{"DATA":"Bình Chánh"},{"DATA":"672458.703937657"},{"DATA":"1194328.47320019"},{"DATA":"7524"},{"DATA":"5"},{"DATA":"QBCT093"}]}, { "COL":[ {"DATA":"C8/28B"},{"DATA":"Võ Văn Vân"},{"DATA":"Bình Chánh"},{"DATA":"672357.289071849"},{"DATA":"1193745.09095592"},{"DATA":"7525"},{"DATA":"6"},{"DATA":"QBCT094"}]}, { "COL":[ {"DATA":"Đối diện C3/1/4"},{"DATA":"Liên ấp 1.2.3"},{"DATA":"Bình Tân"},{"DATA":"672764.277253531"},{"DATA":"1193319.94846954"},{"DATA":"7256"},{"DATA":"7"},{"DATA":"QBTAT241"}]}, { "COL":[ {"DATA":"B12A/31"},{"DATA":"Liên ấp 1.2.3"},{"DATA":"Bình Tân"},{"DATA":"672849.089958279"},{"DATA":"1193028.36601811"},{"DATA":"7255"},{"DATA":"8"},{"DATA":"QBTAT240"}]}, { "COL":[ {"DATA":"B12D/11U"},{"DATA":"Liên ấp 1.2.3"},{"DATA":"Bình Tân"},{"DATA":"672976.561920185"},{"DATA":"1192655.98093967"},{"DATA":"7254"},{"DATA":"9"},{"DATA":"QBTAT239"}]}, { "COL":[ {"DATA":"27/2"},{"DATA":"Liên ấp 1.2.3"},{"DATA":"Bình Tân"},{"DATA":"673102.84475915"},{"DATA":"1192287.08289163"},{"DATA":"7253"},{"DATA":"10"},{"DATA":"QBTAT238"}]}, { "COL":[ {"DATA":"A4/26F"},{"DATA":"Bến Lội"},{"DATA":"Bình Tân"},{"DATA":"673248.13857791"},{"DATA":"1191872.81316466"},{"DATA":"7249"},{"DATA":"11"},{"DATA":"QBTAT234"}]}, { "COL":[ {"DATA":"A5/9C"},{"DATA":"Bến Lội"},{"DATA":"Bình Tân"},{"DATA":"673370.60147766"},{"DATA":"1191562.76019951"},{"DATA":"7248"},{"DATA":"12"},{"DATA":"QBTAT233"}]}, { "COL":[ {"DATA":"11"},{"DATA":"Bến Lội"},{"DATA":"Bình Tân"},{"DATA":"673437.307034738"},{"DATA":"1191257.07927866"},{"DATA":"7247"},{"DATA":"13"},{"DATA":"QBTAT232"}]}, { "COL":[ {"DATA":"45"},{"DATA":"Tân Lân"},{"DATA":"Bình Tân"},{"DATA":"673745.667145058"},{"DATA":"1191077.97399136"},{"DATA":"7245"},{"DATA":"14"},{"DATA":"QBTAT230"}]}, { "COL":[ {"DATA":"950"},{"DATA":"Quốc lộ 1A"},{"DATA":"Bình Tân"},{"DATA":"673955.188272097"},{"DATA":"1190838.8993885"},{"DATA":"7101"},{"DATA":"15"},{"DATA":"QBTAT087"}]}, { "COL":[ {"DATA":"978A"},{"DATA":"Quốc lộ 1A"},{"DATA":"Bình Tân"},{"DATA":"673930.552499689"},{"DATA":"1190159.08244003"},{"DATA":"7102"},{"DATA":"16"},{"DATA":"QBTAT088"}]}, { "COL":[ {"DATA":"1024"},{"DATA":"Quốc lộ 1A"},{"DATA":"Bình Tân"},{"DATA":"674021.654785364"},{"DATA":"1189675.71960304"},{"DATA":"7103"},{"DATA":"17"},{"DATA":"QBTAT089"}]}, { "COL":[ {"DATA":"693"},{"DATA":"Tỉnh lộ 10"},{"DATA":"Bình Tân"},{"DATA":"675991.234166984"},{"DATA":"1189635.56716074"},{"DATA":"7185"},{"DATA":"18"},{"DATA":"QBTAT170"}]}, { "COL":[ {"DATA":"595"},{"DATA":"Tỉnh lộ 10"},{"DATA":"Bình Tân"},{"DATA":"676352.140078704"},{"DATA":"1189679.43398064"},{"DATA":"7186"},{"DATA":"19"},{"DATA":"QBTAT171"}]}, { "COL":[ {"DATA":"485-487"},{"DATA":"Tỉnh lộ 10"},{"DATA":"Bình Tân"},{"DATA":"676657.894897647"},{"DATA":"1189611.38026692"},{"DATA":"7187"},{"DATA":"20"},{"DATA":"QBTAT172"}]}, { "COL":[ {"DATA":"cấp nước Bình Trị Đông"},{"DATA":"Tỉnh lộ 10"},{"DATA":"Bình Tân"},{"DATA":"676951.134965901"},{"DATA":"1189580.28022663"},{"DATA":"7188"},{"DATA":"21"},{"DATA":"QBTAT173"}]}, { "COL":[ {"DATA":"343"},{"DATA":"Tỉnh lộ 10"},{"DATA":"Bình Tân"},{"DATA":"677145.440539099"},{"DATA":"1189562.35954048"},{"DATA":"7189"},{"DATA":"22"},{"DATA":"QBTAT174"}]}, { "COL":[ {"DATA":"9"},{"DATA":"Đường 40"},{"DATA":"Bình Tân"},{"DATA":"675402.483019757"},{"DATA":"1189179.24358624"},{"DATA":"7112"},{"DATA":"23"},{"DATA":"QBTAT098"}]}, { "COL":[ {"DATA":"15"},{"DATA":"Đường 40"},{"DATA":"Bình Tân"},{"DATA":"675403.325597977"},{"DATA":"1189130.27983887"},{"DATA":"7111"},{"DATA":"24"},{"DATA":"QBTAT097"}]}, { "COL":[ {"DATA":"Đối diện 454"},{"DATA":"Đường số 7"},{"DATA":"Bình Tân"},{"DATA":"675565.808099652"},{"DATA":"1189026.78105029"},{"DATA":"7113"},{"DATA":"25"},{"DATA":"QBTAT099"}]}, { "COL":[ {"DATA":"Đối diện 188"},{"DATA":"Đường số 7"},{"DATA":"Bình Tân"},{"DATA":"675873.881064463"},{"DATA":"1189020.81492381"},{"DATA":"7114"},{"DATA":"26"},{"DATA":"QBTAT100"}]}, { "COL":[ {"DATA":"390"},{"DATA":"Tên Lửa"},{"DATA":"Bình Tân"},{"DATA":"676066.046298978"},{"DATA":"1189103.65407075"},{"DATA":"7121"},{"DATA":"27"},{"DATA":"QBTAT107"}]}, { "COL":[ {"DATA":"Đối diện 204"},{"DATA":"Đường số 22"},{"DATA":"Bình Tân"},{"DATA":"676379.056074642"},{"DATA":"1189135.24652493"},{"DATA":"7129"},{"DATA":"28"},{"DATA":"QBTAT115"}]}, { "COL":[ {"DATA":"89"},{"DATA":"Đường số 22"},{"DATA":"Bình Tân"},{"DATA":"676374.439915339"},{"DATA":"1188952.90293093"},{"DATA":"7125"},{"DATA":"29"},{"DATA":"QBTAT111"}]}, { "COL":[ {"DATA":"Đối diện 32"},{"DATA":"Tên Lửa"},{"DATA":"Bình Tân"},{"DATA":"676432.138459356"},{"DATA":"1188077.59318143"},{"DATA":"7119"},{"DATA":"30"},{"DATA":"QBTAT105"}]}, { "COL":[ {"DATA":"Đối diện 14"},{"DATA":"Tên Lửa"},{"DATA":"Bình Tân"},{"DATA":"676532.781146787"},{"DATA":"1187795.96193516"},{"DATA":"7120"},{"DATA":"31"},{"DATA":"QBTAT106"}]}, { "COL":[ {"DATA":"Bệnh viện Triều An"},{"DATA":"Kinh Dương Vương"},{"DATA":"Bình Tân"},{"DATA":"676812.772177447"},{"DATA":"1187665.09761483"},{"DATA":"7021"},{"DATA":"32"},{"DATA":"QBTAT007"}]}, { "COL":[ {"DATA":"Bến xe Miền Tây"},{"DATA":"Kinh Dương Vương"},{"DATA":"Bình Tân"},{"DATA":"676980.863620479"},{"DATA":"1187808.00982691"},{"DATA":"7022"},{"DATA":"33"},{"DATA":"qbtat008"}]}, { "COL":[ {"DATA":"49-51 (317)"},{"DATA":"Kinh Dương Vương"},{"DATA":"Bình Tân"},{"DATA":"677288.861477934"},{"DATA":"1188082.97690156"},{"DATA":"7023"},{"DATA":"34"},{"DATA":"QBTAT009"}]}, { "COL":[ {"DATA":"7"},{"DATA":"Kinh Dương Vương"},{"DATA":"Bình Tân"},{"DATA":"677484.980017796"},{"DATA":"1188251.17992054"},{"DATA":"7024"},{"DATA":"35"},{"DATA":"QBTAT010"}]}, { "COL":[ {"DATA":"1031C"},{"DATA":"Hậu Giang"},{"DATA":"6"},{"DATA":"677957.251131968"},{"DATA":"1188373.59571069"},{"DATA":"8812"},{"DATA":"36"},{"DATA":"Q6T025"}]}, { "COL":[ {"DATA":"919"},{"DATA":"Hậu Giang"},{"DATA":"6"},{"DATA":"678231.041237476"},{"DATA":"1188444.34782974"},{"DATA":"8813"},{"DATA":"37"},{"DATA":"Q6T026"}]}, { "COL":[ {"DATA":"733-735"},{"DATA":"Hậu Giang"},{"DATA":"6"},{"DATA":"678489.044898965"},{"DATA":"1188504.37910972"},{"DATA":"8814"},{"DATA":"38"},{"DATA":"Q6T027"}]}, { "COL":[ {"DATA":"517-519"},{"DATA":"Hậu Giang"},{"DATA":"6"},{"DATA":"678917.0528691"},{"DATA":"1188621.28285586"},{"DATA":"8815"},{"DATA":"39"},{"DATA":"Q6T028"}]}, { "COL":[ {"DATA":"411"},{"DATA":"Hậu Giang"},{"DATA":"6"},{"DATA":"679162.569272851"},{"DATA":"1188684.45947724"},{"DATA":"8816"},{"DATA":"40"},{"DATA":"Q6T029"}]}, { "COL":[ {"DATA":"Đối diện 186"},{"DATA":"Hậu Giang"},{"DATA":"6"},{"DATA":"679642.000865202"},{"DATA":"1188785.39658422"},{"DATA":"8817"},{"DATA":"41"},{"DATA":"Q6T030"}]}, { "COL":[ {"DATA":"131B"},{"DATA":"Hậu Giang"},{"DATA":"6"},{"DATA":"680218.213677492"},{"DATA":"1188769.39210264"},{"DATA":"8818"},{"DATA":"42"},{"DATA":"Q6T031"}]}, { "COL":[ {"DATA":"27"},{"DATA":"Tháp Mười"},{"DATA":"6"},{"DATA":"680705.784254045"},{"DATA":"1188843.13449715"},{"DATA":"8819"},{"DATA":"43"},{"DATA":"Q6T032"}]}, { "COL":[ {"DATA":"13C-13D"},{"DATA":"Tháp Mười"},{"DATA":"6"},{"DATA":"680759.267577251"},{"DATA":"1188854.06157734"},{"DATA":"8820"},{"DATA":"44"},{"DATA":"Q6T033"}]}, { "COL":[ {"DATA":"327"},{"DATA":"Hải Thượng Lãn Ông"},{"DATA":"5"},{"DATA":"680881.395402544"},{"DATA":"1188880.80757794"},{"DATA":"8693"},{"DATA":"45"},{"DATA":"Q5T017"}]}, { "COL":[ {"DATA":"11-12"},{"DATA":"Hải Thượng Lãn Ông"},{"DATA":"5"},{"DATA":"680976.550667914"},{"DATA":"1188903.61866778"},{"DATA":"8694"},{"DATA":"46"},{"DATA":"Q5T018"}]}, { "COL":[ {"DATA":"388"},{"DATA":"Tùng Thiện Vương"},{"DATA":"8"},{"DATA":"681153.135307574"},{"DATA":"1188230.67866061"},{"DATA":"6798"},{"DATA":"47"},{"DATA":"Q8T112"}]}, { "COL":[ {"DATA":"100"},{"DATA":"Quốc lộ 50"},{"DATA":"8"},{"DATA":"681100.76807961"},{"DATA":"1187590.27554409"},{"DATA":"6753"},{"DATA":"48"},{"DATA":"Q8T067"}]}, { "COL":[ {"DATA":"224"},{"DATA":"Quốc lộ 50"},{"DATA":"8"},{"DATA":"681107.587605074"},{"DATA":"1187359.15459164"},{"DATA":"6754"},{"DATA":"49"},{"DATA":"Q8T068"}]}, { "COL":[ {"DATA":"GA HKXB QUẬN 8"},{"DATA":"Quốc lộ 50"},{"DATA":"8"},{"DATA":"681206.811516841"},{"DATA":"1186997.32769963"},{"DATA":"4312"},{"DATA":"50"},{"DATA":"BX20"}]} ]}]}